gcip/__init__.py
gcip/addons/__init__.py
gcip/addons/aws/__init__.py
gcip/addons/aws/helper.py
gcip/addons/aws/jobs/__init__.py
gcip/addons/aws/jobs/cdk.py
gcip/addons/aws/jobs/codecommit.py
gcip/addons/aws/sequences/__init__.py
gcip/addons/aws/sequences/cdk.py
gcip/addons/aws/tools/__init__.py
gcip/addons/aws/tools/wait_for_cloudformation_stack_ready.py
gcip/addons/container/__init__.py
gcip/addons/container/config.py
gcip/addons/container/images.py
gcip/addons/container/registries.py
gcip/addons/container/jobs/__init__.py
gcip/addons/container/jobs/crane.py
gcip/addons/container/jobs/docker.py
gcip/addons/container/jobs/kaniko.py
gcip/addons/container/jobs/trivy.py
gcip/addons/container/sequences/__init__.py
gcip/addons/container/sequences/build.py
gcip/addons/container/sequences/copy.py
gcip/addons/git/__init__.py
gcip/addons/git/jobs/__init__.py
gcip/addons/git/jobs/git.py
gcip/addons/gitlab/__init__.py
gcip/addons/gitlab/jobs/__init__.py
gcip/addons/gitlab/jobs/pages.py
gcip/addons/gitlab/jobs/tags.py
gcip/addons/gitlab/scripts/__init__.py
gcip/addons/linux/__init__.py
gcip/addons/linux/scripts/__init__.py
gcip/addons/linux/scripts/package_manager.py
gcip/addons/notification/__init__.py
gcip/addons/notification/jobs/__init__.py
gcip/addons/notification/jobs/mail.py
gcip/addons/python/__init__.py
gcip/addons/python/jobs/__init__.py
gcip/addons/python/jobs/build.py
gcip/addons/python/jobs/deploy.py
gcip/addons/python/jobs/linter.py
gcip/addons/python/jobs/test.py
gcip/addons/python/scripts/__init__.py
gcip/addons/python/sequences/__init__.py
gcip/addons/security/__init__.py
gcip/addons/security/sops.py
gcip/core/__init__.py
gcip/core/artifacts.py
gcip/core/cache.py
gcip/core/environment.py
gcip/core/image.py
gcip/core/include.py
gcip/core/job.py
gcip/core/need.py
gcip/core/pipeline.py
gcip/core/retry.py
gcip/core/rule.py
gcip/core/sequence.py
gcip/core/service.py
gcip/core/variables.py
gcip/core/when.py
gcip/core/workflow.py
gcip/lib/__init__.py
gcip-9.2.2.dist-info/licenses/LICENCE
gcip-9.2.2.dist-info/METADATA
gcip-9.2.2.dist-info/WHEEL
gcip-9.2.2.dist-info/top_level.txt
gcip-9.2.2.dist-info/RECORD
