Metadata-Version: 2.4
Name: gcip
Version: 9.2.2
Summary: The Gitlab CI Python Library
Home-page: https://gitlab.com/dbsystel/gitlab-ci-python-library
Author: Thomas Steinbach
Author-email: thomas.t.steinbach@deutschebahn.com
Requires-Python: ~=3.11
License-File: LICENCE
Requires-Dist: boto3~=1.17
Requires-Dist: pyaml>=20
Requires-Dist: setuptools-git-versioning~=1.8
Requires-Dist: semver~=3.0
Requires-Dist: python-gitlab~=4.7
Dynamic: author
Dynamic: author-email
Dynamic: description
Dynamic: description-content-type
Dynamic: home-page
Dynamic: license-file
Dynamic: requires-dist
Dynamic: requires-python
Dynamic: summary
